<?xml version="1.0" encoding="UTF-8"?><Pack Name="Armourers" Revision="0"><Marker Name="Warrior's Battle Gear" X="2533" Y="576" Icon="ARMS" Facet="0"/><Marker Name="Angra-Char-In-Lem" X="808" Y="586" Icon="ARMS" Facet="3"/><Marker Name="an armourer" X="1497" Y="614" Icon="ARMS" Facet="3"/><Marker Name="Anglo-In-Lem" X="808" Y="697" Icon="ARMS" Facet="3"/><Marker Name="Warrior's Companion" X="2835" Y="805" Icon="ARMS" Facet="0"/><Marker Name="The Ironworks" X="2865" Y="852" Icon="ARMS" Facet="0"/><Marker Name="The Warrior's Supplies" X="2217" Y="1170" Icon="ARMS" Facet="0"/><Marker Name="Armoury of Souls" X="1984" Y="1367" Icon="BLACKSMITH" Facet="4"/><Marker Name="Artistic Armour" X="1637" Y="1693" Icon="ARMS" Facet="0"/><Marker Name="More Than Just Mail" X="586" Y="2170" Icon="ARMS" Facet="0"/><Marker Name="On Guard Armoury" X="630" Y="2194" Icon="BLACKSMITH" Facet="0"/><Marker Name="Armorer" X="3534" Y="2543" Icon="ARMOURERSGUILD" Facet="2"/><Marker Name="Shining Path Armory" X="1895" Y="2653" Icon="ARMS" Facet="0"/><Marker Name="Honorable Arms" X="1937" Y="2771" Icon="BLACKSMITH" Facet="0"/><Marker Name="The Revenge Shoppe" X="5805" Y="3300" Icon="ARMS" Facet="0"/><Marker Name="Ter Mur Defense Ministry" X="906" Y="3418" Icon="ARMS" Facet="6"/><Marker Name="Serpent's Arms" X="3018" Y="3433" Icon="ARMS" Facet="0"/><Marker Name="Ter Mur Military Academy" X="724" Y="3573" Icon="ARMS" Facet="6"/><Marker Name="Second Skin" X="1441" Y="3719" Icon="ARMS" Facet="0"/><Marker Name="Deadly Intentions" X="1359" Y="3763" Icon="ARMS" Facet="0"/><Marker Name="Jhelom Armory" X="1456" Y="3850" Icon="ARMS" Facet="0"/><Marker Name="Call to Arms" X="1475" Y="3865" Icon="ARMS" Facet="0"/><Marker Name="Armourer" X="1016" Y="3880" Icon="ARMS" Facet="6"/></Pack>